storage/__init__.py
storage/main.py
backend_storage-1.4.1.dist-info/LICENSE
backend_storage-1.4.1.dist-info/METADATA
backend_storage-1.4.1.dist-info/WHEEL
backend_storage-1.4.1.dist-info/top_level.txt
backend_storage-1.4.1.dist-info/RECORD
