Metadata-Version: 2.1
Name: backend-storage
Version: 1.4.1
Summary: 提供了基于 Node.js 开发的 RESTful 接口，可以方便地进行数据的增删改查（CRUD）操作以及高效的数据搜索
License-File: LICENSE
Requires-Dist: requests
Requires-Dist: fastapi
